hi_monk-0.7.0.dist-info/METADATA
hi_monk-0.7.0.dist-info/WHEEL
hi_monk-0.7.0.dist-info/entry_points.txt
hi_monk/__init__.py
hi_monk/hello.py
hi_monk-0.7.0.dist-info/RECORD
