Metadata-Version: 2.1
Name: hi_monk
Version: 0.7.0
Summary: Default template for PDM package
Author-Email: thephunkmonk <andrewchoi1218@gmail.com>
License: MIT
Requires-Python: >=3.9
